yyweaknet/__init__.py
yyweaknet/logger.py
yyweaknet/stf.py
yyweaknet/weaknet.py
yyweaknet-0.2.29.dist-info/METADATA
yyweaknet-0.2.29.dist-info/WHEEL
yyweaknet-0.2.29.dist-info/top_level.txt
yyweaknet-0.2.29.dist-info/RECORD
