Metadata-Version: 2.1
Name: yyweaknet
Version: 0.2.29
Summary: weaknetwork test tools
Home-page: UNKNOWN
Author: lizhidong
Author-email: mblzds@gmail.com
License: UNKNOWN
Platform: UNKNOWN
Classifier: Programming Language :: Python :: 3
Classifier: License :: OSI Approved :: MIT License
Classifier: Operating System :: OS Independent
Requires-Python: >=3.7
